migrate_middleware/__init__.py
migrate_middleware/apps.py
migrate_middleware/conf.py
migrate_middleware/middleware/__init__.py
django_migrate_middleware-3.0.0.dist-info/METADATA
django_migrate_middleware-3.0.0.dist-info/WHEEL
django_migrate_middleware-3.0.0.dist-info/licenses/LICENSE
django_migrate_middleware-3.0.0.dist-info/RECORD
