Metadata-Version: 2.3
Name: django-migrate-middleware
Version: 3.0.0
Summary: Run migrations on every request
Project-URL: Homepage, https://github.com/lukewiwa/django-migrate-middleware
Author-email: lukewiwa <luke.wiwa@gmail.com>
License: MIT License
License-File: LICENSE
Classifier: Framework :: Django
Requires-Python: <4.0,>=3.9
Requires-Dist: django>=4.2
